jpath_finder
