Metadata-Version: 1.1
Name: jpath-finder
Version: 1.0.1
Summary: An implementation of Json Path for python.
Home-page: https://github.com/wapwallace/jpath_finder
Author: William Alvarez
Author-email: alvarezpw@gmail.com
License: Apache 2.0
Keywords: jpath_finder
Platform: UNKNOWN
Classifier: Development Status :: 4 - Beta
Classifier: Intended Audience :: Developers
Classifier: License :: OSI Approved :: Apache Software License
Classifier: Programming Language :: Python :: 2.7
Classifier: Programming Language :: Python :: 3.7
